beetsplug/__init__.py
beetsplug/filetote.py
beetsplug/filetote_dataclasses.py
beetsplug/mapping_model.py
beetsplug/py.typed
beets_filetote-1.1.1.dist-info/LICENSE
beets_filetote-1.1.1.dist-info/METADATA
beets_filetote-1.1.1.dist-info/WHEEL
beets_filetote-1.1.1.dist-info/RECORD
