Metadata-Version: 2.1
Name: beets-filetote
Version: 1.1.1
Summary: A beets plugin to copy/moves non-music extra files, attachments, and artifacts during the import process.
Home-page: https://github.com/gtronset/beets-filetote
License: MIT
Keywords: beets,files,artifacts,extra
Author: Gavin Tronset
Author-email: gtronset@gmail.com
Requires-Python: >=3.9,<4.0
Classifier: Environment :: Console
Classifier: Environment :: Web Environment
Classifier: License :: OSI Approved :: MIT License
Classifier: Programming Language :: Python :: 3
Classifier: Programming Language :: Python :: 3.9
Classifier: Programming Language :: Python :: 3.10
Classifier: Programming Language :: Python :: 3.11
Classifier: Programming Language :: Python :: 3.12
Classifier: Programming Language :: Python :: 3.13
Classifier: Topic :: Multimedia :: Sound/Audio
Classifier: Topic :: Multimedia :: Sound/Audio :: Players :: MP3
Requires-Dist: beets (>=2.3.0,<2.6.0)
Requires-Dist: mediafile (>=0.12.0)
Requires-Dist: typing_extensions ; python_full_version <= "3.10.0"
Project-URL: Documentation, https://github.com/gtronset/beets-filetote
Project-URL: Repository, https://github.com/gtronset/beets-filetote
Project-URL: Release notes, https://github.com/gtronset/beets-filetote/releases
Project-URL: Source, https://github.com/gtronset/beets-filetote
